[{
        "id": 1,
        "name": "Vernonia Schreb.",
        "description": "mauris morbi non lectus aliquam sit amet diam in magna bibendum imperdiet nullam orci pede venenatis non sodales sed tincidunt eu felis fusce posuere felis sed lacus morbi",
        "gender": "Female",
        "category": "indumentaria",
        "sale": false,
        "new": false,
        "size": "S",
        "image": "indu1.png",
        "price": "$3099.74"
    },
    {
        "id": 2,
        "name": "Pachira aquatica Aubl.",
        "description": "phasellus id sapien in sapien iaculis congue vivamus metus arcu adipiscing molestie hendrerit at vulputate vitae nisl aenean lectus pellentesque eget nunc donec quis",
        "gender": null,
        "category": "accesorios",
        "sale": false,
        "new": false,
        "image": "accesorio10.png",
        "price": "$429.81"
    },
    {
        "id": 3,
        "name": "Jepsonia Small",
        "description": "ullamcorper purus sit amet nulla quisque arcu libero rutrum ac lobortis vel dapibus at diam nam tristique tortor eu pede",
        "gender": null,
        "category": "accesorios",
        "sale": true,
        "new": false,
        "image": "accesorio11.png",
        "price": "$2040.49"
    },
    {
        "id": 4,
        "name": "Plagiobothrys leptocladus (Greene) I.M. Johnst.",
        "description": "amet diam in magna bibendum imperdiet nullam orci pede venenatis non sodales sed tincidunt",
        "gender": "Female",
        "category": "indumentaria",
        "sale": false,
        "new": false,
        "size": "M",
        "image": "indu2.png",
        "price": "$1398.67"
    },
    {
        "id": 5,
        "name": "Aspicilia heteroplaca (Zahlbr.) Oksner",
        "description": "quam sollicitudin vitae consectetuer eget rutrum at lorem integer tincidunt ante vel",
        "gender": "Male",
        "category": "indumentaria",
        "sale": true,
        "new": false,
        "size": "L",
        "image": "indu4.png",
        "price": "$2496.91"
    },
    {
        "id": 6,
        "name": "Caltha palustris L.",
        "description": "dui proin leo odio porttitor id consequat in consequat ut nulla sed accumsan felis ut at dolor quis",
        "gender": "Female",
        "category": "indumentaria",
        "sale": false,
        "new": false,
        "size": "X",
        "image": "indu3.png",
        "price": "$4560.25"
    },
    {
        "id": 7,
        "name": "Calochortus greenei S. Watson",
        "description": "ipsum primis in faucibus orci luctus et ultrices posuere cubilia curae donec pharetra magna vestibulum aliquet ultrices erat tortor sollicitudin mi sit amet lobortis sapien sapien non",
        "gender": "Male",
        "category": "indumentaria",
        "sale": true,
        "new": false,
        "image": "indu5.png",
        "price": "$316.77"
    },
    {
        "id": 8,
        "name": "Salix pseudomonticola C.R. Ball",
        "description": "sapien quis libero nullam sit amet turpis elementum ligula vehicula consequat morbi a ipsum integer a nibh in quis justo maecenas rhoncus aliquam lacus morbi quis",
        "gender": null,
        "category": "bijouterie",
        "sale": true,
        "new": false,
        "image": "bijoux10.png",
        "price": "$253.64"
    },
    {
        "id": 9,
        "name": "Leptogium sessile Vain.",
        "description": "tortor quis turpis sed ante vivamus tortor duis mattis egestas metus aenean fermentum donec ut mauris eget massa tempor convallis nulla neque",
        "gender": "Male",
        "category": "indumentaria",
        "sale": true,
        "new": false,
        "image": "indu6.png",
        "price": "$2285.61"
    },
    {
        "id": 10,
        "name": "Crataegus knieskerniana Sarg.",
        "description": "bibendum felis sed interdum venenatis turpis enim blandit mi in porttitor pede justo eu massa donec dapibus duis at velit eu est congue elementum in hac habitasse platea dictumst",
        "gender": null,
        "category": "bijouterie",
        "sale": true,
        "new": true,
        "image": "bijoux9.png",
        "price": "$2411.48"
    },
    {
        "id": 11,
        "name": "Polystachya concreta (Jacq.) Garay & H.R. Sweet",
        "description": "faucibus orci luctus et ultrices posuere cubilia curae duis faucibus accumsan odio curabitur convallis duis consequat dui nec nisi volutpat eleifend donec ut dolor morbi vel lectus in",
        "gender": "Female",
        "category": "indumentaria",
        "sale": true,
        "new": false,
        "image": "indu7.png",
        "price": "$4405.85"
    },
    {
        "id": 12,
        "name": "Cryptocoryne Fisch. ex Wydl.",
        "description": "maecenas pulvinar lobortis est phasellus sit amet erat nulla tempus vivamus in felis eu sapien cursus vestibulum proin",
        "gender": "Female",
        "category": "indumentaria",
        "sale": false,
        "new": true,
        "image": "indu8.png",
        "price": "$4317.68"
    },
    {
        "id": 13,
        "name": "Philadelphus texensis Hu",
        "description": "accumsan odio curabitur convallis duis consequat dui nec nisi volutpat eleifend donec ut",
        "gender": "Female",
        "category": "indumentaria",
        "sale": true,
        "new": false,
        "image": "indu9.png",
        "price": "$3827.53"
    },
    {
        "id": 14,
        "name": "Dioscorea nummularia Lam.",
        "description": "morbi non lectus aliquam sit amet diam in magna bibendum imperdiet nullam orci pede venenatis non sodales sed tincidunt eu felis fusce posuere felis sed lacus morbi",
        "gender": "Female",
        "category": "indumentaria",
        "sale": true,
        "new": false,
        "image": "indu10.png",
        "price": "$5200.45"
    },
    {
        "id": 15,
        "name": "Geheebia gigantea (Funck) Boul.",
        "description": "et ultrices posuere cubilia curae duis faucibus accumsan odio curabitur convallis duis",
        "gender": null,
        "category": "bijouterie",
        "sale": true,
        "new": true,
        "image": "bijoux8.png",
        "price": "$635.75"
    },
    {
        "id": 16,
        "name": "Ribes diacanthum Pall.",
        "description": "ut volutpat sapien arcu sed augue aliquam erat volutpat in",
        "gender": "Male",
        "category": "indumentaria",
        "sale": true,
        "new": true,
        "image": "/pede/ullamcorper/augue/a/suscipit/nulla/elit.jpg",
        "price": "$3576.76"
    },
    {
        "id": 17,
        "name": "Sphaeromeria Nutt.",
        "description": "nam nulla integer pede justo lacinia eget tincidunt eget tempus vel pede morbi porttitor lorem id ligula suspendisse ornare consequat lectus in est risus auctor sed tristique in tempus",
        "gender": "Female",
        "category": "indumentaria",
        "sale": true,
        "new": false,
        "image": "/justo/etiam/pretium/iaculis.xml",
        "price": "$5431.06"
    },
    {
        "id": 18,
        "name": "Zizia aptera (A. Gray) Fernald",
        "description": "lectus in quam fringilla rhoncus mauris enim leo rhoncus sed vestibulum sit",
        "gender": null,
        "category": "home",
        "sale": false,
        "new": false,
        "image": "/neque/libero/convallis/eget/eleifend.xml",
        "price": "$4261.68"
    },
    {
        "id": 19,
        "name": "Eryngium baldwinii Spreng.",
        "description": "elementum pellentesque quisque porta volutpat erat quisque erat eros viverra eget congue eget semper rutrum nulla nunc purus",
        "gender": null,
        "category": "home",
        "sale": true,
        "new": false,
        "image": "/magna/at/nunc/commodo/placerat.html",
        "price": "$1252.08"
    },
    {
        "id": 20,
        "name": "Anisomeridium carinthiacum (J. Steiner) R.C. Harris",
        "description": "cum sociis natoque penatibus et magnis dis parturient montes nascetur ridiculus mus vivamus vestibulum sagittis sapien cum sociis natoque",
        "gender": null,
        "category": "accesorios",
        "sale": false,
        "new": false,
        "image": "accesorio9.png",
        "price": "$5017.47"
    },
    {
        "id": 21,
        "name": "Polygala alba Nutt.",
        "description": "augue aliquam erat volutpat in congue etiam justo etiam pretium iaculis justo in hac habitasse platea dictumst etiam",
        "gender": "Female",
        "category": "indumentaria",
        "sale": false,
        "new": false,
        "image": "/suscipit/ligula/in.html",
        "price": "$1522.78"
    },
    {
        "id": 22,
        "name": "Caloplaca trachyphylla (Tuck.) Zahlbr.",
        "description": "velit nec nisi vulputate nonummy maecenas tincidunt lacus at velit vivamus vel nulla eget eros elementum pellentesque quisque porta volutpat erat quisque",
        "gender": null,
        "category": "accesorios",
        "sale": false,
        "new": true,
        "image": "accesorio8.png",
        "price": "$4844.29"
    },
    {
        "id": 23,
        "name": "Malvaviscus arboreus Dill. ex Cav. var. arboreus",
        "description": "ante ipsum primis in faucibus orci luctus et ultrices posuere cubilia curae donec pharetra magna",
        "gender": null,
        "category": "home",
        "sale": true,
        "new": false,
        "image": "/cursus/urna/ut/tellus.aspx",
        "price": "$4492.26"
    },
    {
        "id": 24,
        "name": "Eriogonum umbellatum Torr. var. goodmanii Reveal",
        "description": "congue etiam justo etiam pretium iaculis justo in hac habitasse platea dictumst etiam faucibus cursus urna ut tellus nulla ut",
        "gender": null,
        "category": "bijouterie",
        "sale": true,
        "new": false,
        "image": "bijoux7.png",
        "price": "$4037.65"
    },
    {
        "id": 25,
        "name": "Rhizocarpon badioatrum (Flörke ex Spreng.) Th. Fr.",
        "description": "proin at turpis a pede posuere nonummy integer non velit donec diam neque vestibulum",
        "gender": "Female",
        "category": "indumentaria",
        "sale": false,
        "new": true,
        "image": "/aliquam.json",
        "price": "$2455.34"
    },
    {
        "id": 26,
        "name": "Gilia ochroleuca M.E. Jones ssp. bizonata A.D. Grant & V.E. Grant",
        "description": "praesent blandit nam nulla integer pede justo lacinia eget tincidunt eget tempus vel pede morbi",
        "gender": "Female",
        "category": "indumentaria",
        "sale": true,
        "new": true,
        "image": "/nullam/molestie/nibh/in/lectus/pellentesque/at.xml",
        "price": "$5450.66"
    },
    {
        "id": 27,
        "name": "Xylographa disseminata Willey",
        "description": "faucibus orci luctus et ultrices posuere cubilia curae donec pharetra magna vestibulum aliquet ultrices erat tortor sollicitudin",
        "gender": null,
        "category": "home",
        "sale": true,
        "new": true,
        "image": "/accumsan/felis/ut/at/dolor.js",
        "price": "$466.70"
    },
    {
        "id": 28,
        "name": "Fumaria parviflora Lam.",
        "description": "facilisi cras non velit nec nisi vulputate nonummy maecenas tincidunt lacus at velit vivamus vel nulla eget eros elementum pellentesque quisque porta volutpat erat quisque erat",
        "gender": "Male",
        "category": "indumentaria",
        "sale": true,
        "new": true,
        "image": "/dis/parturient/montes/nascetur.aspx",
        "price": "$867.88"
    },
    {
        "id": 29,
        "name": "Vesicularia vesicularis (Schwägr.) Broth.",
        "description": "etiam justo etiam pretium iaculis justo in hac habitasse platea dictumst etiam faucibus cursus urna ut tellus nulla ut erat id mauris vulputate",
        "gender": null,
        "category": "bijouterie",
        "sale": true,
        "new": false,
        "image": "bijoux6.png",
        "price": "$817.63"
    },
    {
        "id": 30,
        "name": "Neraudia angulata Cowan var. angulata",
        "description": "blandit lacinia erat vestibulum sed magna at nunc commodo placerat praesent blandit nam nulla integer pede justo lacinia eget tincidunt eget tempus vel pede morbi porttitor lorem id ligula",
        "gender": null,
        "category": "accesorios",
        "sale": true,
        "new": false,
        "image": "accesorio7.png",
        "price": "$1896.69"
    },
    {
        "id": 31,
        "name": "Lathyrus nevadensis S. Watson ssp. lanceolatus (Howell) C.L. Hitchc. var. parkeri (H. St. John) C.L. Hitchc.",
        "description": "malesuada in imperdiet et commodo vulputate justo in blandit ultrices enim lorem ipsum dolor sit amet consectetuer adipiscing elit proin interdum mauris non ligula pellentesque ultrices phasellus id",
        "gender": null,
        "category": "home",
        "sale": false,
        "new": false,
        "image": "hogar4.png",
        "price": "$4740.55"
    },
    {
        "id": 32,
        "name": "Clintonia andrewsiana Torr.",
        "description": "duis consequat dui nec nisi volutpat eleifend donec ut dolor morbi vel lectus in",
        "gender": "Female",
        "category": "indumentaria",
        "sale": false,
        "new": true,
        "image": "/non/mauris/morbi/non/lectus/aliquam/sit.jsp",
        "price": "$3439.61"
    },
    {
        "id": 33,
        "name": "Aristolochia grandiflora Sw.",
        "description": "nisl nunc rhoncus dui vel sem sed sagittis nam congue risus semper porta volutpat quam pede lobortis ligula sit amet eleifend pede libero quis orci",
        "gender": "Male",
        "category": "indumentaria",
        "sale": true,
        "new": false,
        "image": "/vivamus.html",
        "price": "$3995.61"
    },
    {
        "id": 34,
        "name": "Clinopodium L.",
        "description": "ultrices posuere cubilia curae duis faucibus accumsan odio curabitur convallis duis consequat dui nec nisi volutpat eleifend donec ut dolor morbi vel lectus in quam fringilla rhoncus mauris",
        "gender": null,
        "category": "home",
        "sale": false,
        "new": true,
        "image": "hogar3.png",
        "price": "$2955.59"
    },
    {
        "id": 35,
        "name": "Allium canadense L. var. ecristatum (M.E. Jones) Ownbey",
        "description": "pellentesque ultrices mattis odio donec vitae nisi nam ultrices libero non mattis pulvinar nulla pede ullamcorper augue a suscipit nulla elit ac nulla sed vel enim",
        "gender": null,
        "category": "accesorios",
        "sale": false,
        "new": true,
        "image": "accesorio6.png",
        "price": "$5122.23"
    },
    {
        "id": 36,
        "name": "Juncus bulbosus L.",
        "description": "neque duis bibendum morbi non quam nec dui luctus rutrum nulla tellus in sagittis dui vel nisl duis ac nibh fusce lacus purus aliquet at feugiat non",
        "gender": null,
        "category": "home",
        "sale": false,
        "new": true,
        "image": "hogar2.png",
        "price": "$3975.98"
    },
    {
        "id": 37,
        "name": "Tournefortia hirsutissima L.",
        "description": "sed ante vivamus tortor duis mattis egestas metus aenean fermentum donec ut mauris eget massa tempor convallis nulla neque libero convallis eget eleifend luctus ultricies eu nibh",
        "gender": null,
        "category": "bijouterie",
        "sale": false,
        "new": true,
        "image": "bijuox5.png",
        "price": "$3778.51"
    },
    {
        "id": 38,
        "name": "Pycnanthemum verticillatum (Michx.) Pers. var. pilosum (Nutt.) Cooperr.",
        "description": "pede morbi porttitor lorem id ligula suspendisse ornare consequat lectus in est risus auctor sed tristique in tempus sit amet sem fusce consequat nulla nisl nunc nisl duis",
        "gender": null,
        "category": "accesorios",
        "sale": true,
        "new": false,
        "image": "accesorio5.png",
        "price": "$1935.60"
    },
    {
        "id": 39,
        "name": "Physcomitrium collenchymatum Gier",
        "description": "consequat varius integer ac leo pellentesque ultrices mattis odio donec vitae nisi nam ultrices",
        "gender": null,
        "category": "home",
        "sale": false,
        "new": false,
        "image": "hogar1.png",
        "price": "$4138.76"
    },
    {
        "id": 40,
        "name": "Amberboa (Pers.) Less.",
        "description": "dolor vel est donec odio justo sollicitudin ut suscipit a feugiat",
        "gender": "Female",
        "category": "indumentaria",
        "sale": false,
        "new": true,
        "image": "/vel/sem/sed/sagittis/nam.json",
        "price": "$4783.18"
    },
    {
        "id": 41,
        "name": "Chorizanthe diffusa Benth.",
        "description": "non lectus aliquam sit amet diam in magna bibendum imperdiet nullam orci pede venenatis",
        "gender": null,
        "category": "bijouterie",
        "sale": false,
        "new": true,
        "image": "bijoux4.png",
        "price": "$2536.74"
    },
    {
        "id": 42,
        "name": "Vallisneria L.",
        "description": "lacinia sapien quis libero nullam sit amet turpis elementum ligula vehicula",
        "gender": null,
        "category": "accesorios",
        "sale": true,
        "new": true,
        "image": "accesorio4.png",
        "price": "$626.77"
    },
    {
        "id": 43,
        "name": "Aureolaria grandiflora (Benth.) Pennell var. serrata (Torr. ex Benth.) Pennell",
        "description": "venenatis tristique fusce congue diam id ornare imperdiet sapien urna pretium nisl ut volutpat sapien arcu sed augue aliquam",
        "gender": null,
        "category": "accesorios",
        "sale": false,
        "new": true,
        "image": "accesorio3.png",
        "price": "$4464.20"
    },
    {
        "id": 44,
        "name": "Verbascum nigrum L.",
        "description": "nisi eu orci mauris lacinia sapien quis libero nullam sit amet turpis elementum ligula vehicula consequat morbi a ipsum integer a",
        "gender": "Female",
        "category": "indumentaria",
        "sale": false,
        "new": false,
        "image": "/id/ornare/imperdiet/sapien/urna/pretium.jsp",
        "price": "$1309.46"
    },
    {
        "id": 45,
        "name": "Grimmia montana Bruch & Schimp.",
        "description": "eros viverra eget congue eget semper rutrum nulla nunc purus phasellus in felis donec semper sapien a libero nam dui proin leo odio porttitor",
        "gender": null,
        "category": "bijouterie",
        "sale": false,
        "new": true,
        "image": "bijoux3.png",
        "price": "$2824.76"
    },
    {
        "id": 46,
        "name": "Herbertia lahue (Molina) Goldblatt",
        "description": "luctus cum sociis natoque penatibus et magnis dis parturient montes nascetur ridiculus mus vivamus vestibulum sagittis sapien cum sociis natoque penatibus et magnis dis parturient montes",
        "gender": "Male",
        "category": "indumentaria",
        "sale": true,
        "new": false,
        "image": "/libero/nullam/sit.json",
        "price": "$3898.23"
    },
    {
        "id": 47,
        "name": "Cardaminopsis Hayek",
        "description": "elementum in hac habitasse platea dictumst morbi vestibulum velit id pretium iaculis diam erat",
        "gender": null,
        "category": "bijouterie",
        "sale": false,
        "new": true,
        "image": "bijoux2.png",
        "price": "$5384.05"
    },
    {
        "id": 48,
        "name": "Eriophyllum mohavense (I.M. Johnst.) Jeps.",
        "description": "metus sapien ut nunc vestibulum ante ipsum primis in faucibus orci luctus et",
        "gender": null,
        "category": "accesorios",
        "sale": false,
        "new": false,
        "image": "accesorio2.png",
        "price": "$1477.29"
    },
    {
        "id": 49,
        "name": "Rubus fryei H.A. Davis & T. Davis",
        "description": "mi sit amet lobortis sapien sapien non mi integer ac neque duis bibendum morbi non quam nec dui luctus rutrum nulla",
        "gender": null,
        "category": "accesorios",
        "sale": true,
        "new": true,
        "image": "accesorio1.png",
        "price": "$4901.10"
    },
    {
        "id": 50,
        "name": "Juncus saximontanus A. Nelson",
        "description": "condimentum id luctus nec molestie sed justo pellentesque viverra pede ac diam cras pellentesque volutpat dui maecenas tristique est et tempus",
        "gender": null,
        "category": "bijouterie",
        "sale": true,
        "new": true,
        "image": "bijoux1.png",
        "price": "$3582.10"
    },
    {
        "id": 51,
        "name": "Marcosdasd",
        "price": "88908098",
        "category": "indumentaria",
        "size": "",
        "gender": "",
        "description": " ipoidpofiapsdo fipaosdi faposdi faposid fapsoidf a",
        "image": []
    }

]